stistarg/__init__.py
stistarg/_version.py
stistarg/main.py
stistarg/test_stistarg.py
stistarg-2.4.1.dist-info/licenses/LICENSE.txt
stistarg-2.4.1.dist-info/METADATA
stistarg-2.4.1.dist-info/WHEEL
stistarg-2.4.1.dist-info/entry_points.txt
stistarg-2.4.1.dist-info/top_level.txt
stistarg-2.4.1.dist-info/RECORD
