Metadata-Version: 2.4
Name: stistarg
Version: 2.4.1
Summary: HST/STIS Target Acquisition Simulator
Author: Bralen Berry
Author-email: Sean Lockwood <lockwood@stsci.edu>
Maintainer-email: Sean Lockwood <lockwood@stsci.edu>
License: Copyright (C) 2017 Association of Universities for Research in Astronomy (AURA)
Project-URL: Homepage, http://www.stsci.edu/instruments/stis
Project-URL: Documentation, https://stistarg.readthedocs.io
Project-URL: Support, https://hsthelp.stsci.edu
Keywords: astronomy
Classifier: Programming Language :: Python
Classifier: Programming Language :: Python :: 3.9
Classifier: Programming Language :: Python :: 3.10
Classifier: Programming Language :: Python :: 3.11
Classifier: Programming Language :: Python :: 3.12
Classifier: Development Status :: 5 - Production/Stable
Classifier: Operating System :: OS Independent
Classifier: Intended Audience :: Science/Research
Classifier: License :: OSI Approved :: BSD License
Classifier: Topic :: Scientific/Engineering :: Astronomy
Classifier: Topic :: Scientific/Engineering :: Physics
Classifier: Topic :: Software Development :: Libraries :: Python Modules
Requires-Python: >=3.9
License-File: LICENSE.txt
Requires-Dist: setuptools
Requires-Dist: numpy
Requires-Dist: astropy
Requires-Dist: matplotlib
Provides-Extra: docs
Requires-Dist: sphinx; extra == "docs"
Provides-Extra: test
Requires-Dist: pytest; extra == "test"
Requires-Dist: pytest-cov; extra == "test"
Dynamic: license-file
